pybind11/__init__.py
pybind11/__main__.py
pybind11/_version.py
pybind11/_version.pyi
pybind11/commands.py
pybind11/py.typed
pybind11/setup_helpers.py
pybind11/setup_helpers.pyi
pybind11/include/pybind11/attr.h
pybind11/include/pybind11/buffer_info.h
pybind11/include/pybind11/cast.h
pybind11/include/pybind11/chrono.h
pybind11/include/pybind11/common.h
pybind11/include/pybind11/complex.h
pybind11/include/pybind11/eigen.h
pybind11/include/pybind11/embed.h
pybind11/include/pybind11/eval.h
pybind11/include/pybind11/functional.h
pybind11/include/pybind11/iostream.h
pybind11/include/pybind11/numpy.h
pybind11/include/pybind11/operators.h
pybind11/include/pybind11/options.h
pybind11/include/pybind11/pybind11.h
pybind11/include/pybind11/pytypes.h
pybind11/include/pybind11/stl.h
pybind11/include/pybind11/stl_bind.h
pybind11/include/pybind11/detail/class.h
pybind11/include/pybind11/detail/common.h
pybind11/include/pybind11/detail/descr.h
pybind11/include/pybind11/detail/init.h
pybind11/include/pybind11/detail/internals.h
pybind11/include/pybind11/detail/typeid.h
pybind11/share/cmake/pybind11/FindPythonLibsNew.cmake
pybind11/share/cmake/pybind11/pybind11Common.cmake
pybind11/share/cmake/pybind11/pybind11Config.cmake
pybind11/share/cmake/pybind11/pybind11ConfigVersion.cmake
pybind11/share/cmake/pybind11/pybind11NewTools.cmake
pybind11/share/cmake/pybind11/pybind11Targets.cmake
pybind11/share/cmake/pybind11/pybind11Tools.cmake
pybind11_rosetta_commons-2.6.0.dist-info/LICENSE
pybind11_rosetta_commons-2.6.0.dist-info/METADATA
pybind11_rosetta_commons-2.6.0.dist-info/WHEEL
pybind11_rosetta_commons-2.6.0.dist-info/entry_points.txt
pybind11_rosetta_commons-2.6.0.dist-info/top_level.txt
pybind11_rosetta_commons-2.6.0.dist-info/RECORD
