Metadata-Version: 2.1
Name: pybind11-rosetta-commons
Version: 2.6.0
Summary: Seamless operability between C++11 and Python
Home-page: https://github.com/pybind/pybind11
Download-URL: https://github.com/pybind/pybind11/tarball/v2.6.0
Author: Wenzel Jakob
Author-email: wenzel.jakob@epfl.ch
License: BSD
Keywords: C++11,Python bindings
Platform: UNKNOWN
Classifier: Development Status :: 5 - Production/Stable
Classifier: Intended Audience :: Developers
Classifier: Topic :: Software Development :: Libraries :: Python Modules
Classifier: Topic :: Utilities
Classifier: Programming Language :: C++
Classifier: Programming Language :: Python :: 2.7
Classifier: Programming Language :: Python :: 3
Classifier: Programming Language :: Python :: 3.5
Classifier: Programming Language :: Python :: 3.6
Classifier: Programming Language :: Python :: 3.7
Classifier: Programming Language :: Python :: 3.8
Classifier: License :: OSI Approved :: BSD License
Classifier: Programming Language :: Python :: Implementation :: PyPy
Classifier: Programming Language :: Python :: Implementation :: CPython
Classifier: Programming Language :: C++
Classifier: Topic :: Software Development :: Libraries :: Python Modules
Requires-Python: !=3.0,!=3.1,!=3.2,!=3.3,!=3.4,!=3.9.0,>=2.7
License-File: LICENSE
Provides-Extra: global
Requires-Dist: pybind11-global (==2.6.0) ; extra == 'global'
